github_poster/__init__.py
github_poster/__main__.py
github_poster/circluar_drawer.py
github_poster/cli.py
github_poster/config.py
github_poster/drawer.py
github_poster/err.py
github_poster/poster.py
github_poster/structures.py
github_poster/utils.py
github_poster/html_parser/__init__.py
github_poster/html_parser/github_parser.py
github_poster/html_parser/gitlab_parser.py
github_poster/html_parser/jike_parse.py
github_poster/html_parser/kindle_parser.py
github_poster/loader/__init__.py
github_poster/loader/apple_health_loader.py
github_poster/loader/autosleep_loader.py
github_poster/loader/base_loader.py
github_poster/loader/bbdc_loader.py
github_poster/loader/bilibili_loader.py
github_poster/loader/chatgpt_loader.py
github_poster/loader/cichang_loader.py
github_poster/loader/config.py
github_poster/loader/covid_loader.py
github_poster/loader/dota2_loader.py
github_poster/loader/duolingo_loader.py
github_poster/loader/forest_loader.py
github_poster/loader/from_github_issue_loader.py
github_poster/loader/garmin_loader.py
github_poster/loader/github_loader.py
github_poster/loader/gitlab_loader.py
github_poster/loader/gpx_loader.py
github_poster/loader/jike_loader.py
github_poster/loader/json_loader.py
github_poster/loader/kindle_loader.py
github_poster/loader/leetcode_loader.py
github_poster/loader/multiple_loader.py
github_poster/loader/neodb_loader.py
github_poster/loader/notion_loader.py
github_poster/loader/nrc_loader.py
github_poster/loader/ns_loader.py
github_poster/loader/openlanguage_loader.py
github_poster/loader/shanbay_loader.py
github_poster/loader/strava_loader.py
github_poster/loader/summary_loader.py
github_poster/loader/todoist_loader.py
github_poster/loader/wakatime_loader.py
github_poster/loader/weread_loader.py
github_poster/loader/youtube_loader.py
github_poster/skyline/__init__.py
github_poster/skyline/config.py
github_poster/skyline/skyline.py
github_poster/skyline/font/__init__.py
tests/__init__.py
tests/test_poster_utils.py
github_poster-2.7.4.dist-info/LICENSE
github_poster-2.7.4.dist-info/METADATA
github_poster-2.7.4.dist-info/WHEEL
github_poster-2.7.4.dist-info/entry_points.txt
github_poster-2.7.4.dist-info/top_level.txt
github_poster-2.7.4.dist-info/RECORD
