Metadata-Version: 2.1
Name: github_poster
Version: 2.7.4
Summary: Make everything a GitHub svg poster and Skyline!
Home-page: https://github.com/yihong0618/GitHubPoster
Author: yihong0618
Author-email: zouzou0208@gmail.com
License: MIT
License-File: LICENSE
Requires-Dist: requests
Requires-Dist: svgwrite
Requires-Dist: pendulum ==3.0.0
Requires-Dist: colour
Provides-Extra: all
Requires-Dist: garminconnect ==0.2.12 ; extra == 'all'
Requires-Dist: gpxpy ; extra == 'all'
Requires-Dist: stravalib ==1.0.0 ; extra == 'all'
Requires-Dist: PyGithub ; extra == 'all'
Requires-Dist: sdf-fork ; extra == 'all'
Requires-Dist: pandas ; extra == 'all'
Provides-Extra: garmin
Requires-Dist: garminconnect ; extra == 'garmin'
Provides-Extra: github
Requires-Dist: PyGithub ; extra == 'github'
Provides-Extra: gpx
Requires-Dist: gpxpy ; extra == 'gpx'
Provides-Extra: skyline
Requires-Dist: sdf-fork ; extra == 'skyline'
Provides-Extra: strava
Requires-Dist: stravalib ; extra == 'strava'
Provides-Extra: todoist
Requires-Dist: pandas ; extra == 'todoist'
